{
  "_class": "shapePath",
  "booleanOperation": 0,
  "clippingMaskMode": 0,
  "do_objectID": "C549B4BC-AE99-4988-888B-B1C085DFB658",
  "edited": true,
  "exportOptions": {
    "_class": "exportOptions",
    "exportFormats": [
    ],
    "includedLayerIds": [
    ],
    "layerOptions": 0,
    "shouldTrim": false
  },
  "frame": {
    "_class": "rect",
    "constrainProportions": false,
    "height": 168.4039591836734,
    "width": 235.397,
    "x": 347.3883000000001,
    "y": 0.0003306122449089344
  },
  "hasClippingMask": false,
  "isClosed": true,
  "isFixedToViewport": false,
  "isFlippedHorizontal": false,
  "isFlippedVertical": false,
  "isLocked": false,
  "isVisible": true,
  "layerListExpandedType": 0,
  "name": "Path",
  "nameIsFixed": false,
  "pointRadiusBehaviour": 0,
  "points": [
    {
      "_class": "curvePoint",
      "cornerRadius": 0,
      "curveFrom": "{1, 1}",
      "curveMode": 1,
      "curveTo": "{1, 1}",
      "hasCurveFrom": false,
      "hasCurveTo": false,
      "point": "{1, 1}"
    },
    {
      "_class": "curvePoint",
      "cornerRadius": 0,
      "curveFrom": "{0.7408463149487885, 1}",
      "curveMode": 1,
      "curveTo": "{0.7408463149487885, 1}",
      "hasCurveFrom": false,
      "hasCurveTo": false,
      "point": "{0.7408463149487885, 1}"
    },
    {
      "_class": "curvePoint",
      "cornerRadius": 0,
      "curveFrom": "{0.54869858154521933, 0.54577713646268911}",
      "curveMode": 1,
      "curveTo": "{0.54869858154521933, 0.54577713646268911}",
      "hasCurveFrom": false,
      "hasCurveTo": false,
      "point": "{0.54869858154521933, 0.54577713646268911}"
    },
    {
      "_class": "curvePoint",
      "cornerRadius": 0,
      "curveFrom": "{0.24304897683487905, 1}",
      "curveMode": 1,
      "curveTo": "{0.24304897683487905, 1}",
      "hasCurveFrom": false,
      "hasCurveTo": false,
      "point": "{0.24304897683487905, 1}"
    },
    {
      "_class": "curvePoint",
      "cornerRadius": 0,
      "curveFrom": "{0, 1}",
      "curveMode": 1,
      "curveTo": "{0, 1}",
      "hasCurveFrom": false,
      "hasCurveTo": false,
      "point": "{0, 1}"
    },
    {
      "_class": "curvePoint",
      "cornerRadius": 0,
      "curveFrom": "{0.45097855962480404, 0.40702240021987929}",
      "curveMode": 1,
      "curveTo": "{0.45097855962480404, 0.40702240021987929}",
      "hasCurveFrom": false,
      "hasCurveTo": false,
      "point": "{0.45097855962480404, 0.40702240021987929}"
    },
    {
      "_class": "curvePoint",
      "cornerRadius": 0,
      "curveFrom": "{0.27386500252764473, 0}",
      "curveMode": 1,
      "curveTo": "{0.27386500252764473, 0}",
      "hasCurveFrom": false,
      "hasCurveTo": false,
      "point": "{0.27386500252764473, 0}"
    },
    {
      "_class": "curvePoint",
      "cornerRadius": 0,
      "curveFrom": "{0.45687922955687627, 0}",
      "curveMode": 1,
      "curveTo": "{0.45687922955687627, 0}",
      "hasCurveFrom": false,
      "hasCurveTo": false,
      "point": "{0.45687922955687627, 0}"
    },
    {
      "_class": "curvePoint",
      "cornerRadius": 0,
      "curveFrom": "{0.58998627849972585, 0.29117341029114385}",
      "curveMode": 1,
      "curveTo": "{0.58998627849972585, 0.29117341029114385}",
      "hasCurveFrom": false,
      "hasCurveTo": false,
      "point": "{0.58998627849972585, 0.29117341029114385}"
    },
    {
      "_class": "curvePoint",
      "cornerRadius": 0,
      "curveFrom": "{0.79080447074516658, 0}",
      "curveMode": 1,
      "curveTo": "{0.79080447074516658, 0}",
      "hasCurveFrom": false,
      "hasCurveTo": false,
      "point": "{0.79080447074516658, 0}"
    },
    {
      "_class": "curvePoint",
      "cornerRadius": 0,
      "curveFrom": "{0.9695365701347084, 0}",
      "curveMode": 1,
      "curveTo": "{0.9695365701347084, 0}",
      "hasCurveFrom": false,
      "hasCurveTo": false,
      "point": "{0.9695365701347084, 0}"
    },
    {
      "_class": "curvePoint",
      "cornerRadius": 0,
      "curveFrom": "{0.68812686652761079, 0.41829613051416453}",
      "curveMode": 1,
      "curveTo": "{0.68812686652761079, 0.41829613051416453}",
      "hasCurveFrom": false,
      "hasCurveTo": false,
      "point": "{0.68812686652761079, 0.41829613051416453}"
    }
  ],
  "resizingConstraint": 63,
  "resizingType": 0,
  "rotation": 0,
  "shouldBreakMaskChain": false,
  "style": {
    "_class": "style",
    "endMarkerType": 0,
    "fills": [
      {
        "_class": "fill",
        "color": {
          "_class": "color",
          "alpha": 1,
          "blue": 1,
          "green": 1,
          "red": 1
        },
        "fillType": 0,
        "isEnabled": true,
        "noiseIndex": 0,
        "noiseIntensity": 0,
        "patternFillType": 1,
        "patternTileScale": 1
      }
    ],
    "miterLimit": 10,
    "startMarkerType": 0,
    "windingRule": 1
  },
  "userInfo": {
    "com.animaapp.stc-sketch-plugin": {
      "kModelPropertiesKey": {
      }
    }
  }
}